grobl/__init__.py
grobl/main.py
grobl-0.1.0.dist-info/METADATA
grobl-0.1.0.dist-info/WHEEL
grobl-0.1.0.dist-info/entry_points.txt
grobl-0.1.0.dist-info/RECORD
