Metadata-Version: 2.3
Name: grobl
Version: 0.1.0
Summary: A script to display directory structure and Python file contents
Author-email: Joseph M Courtney <joseph.m.courtney@gmail.com>
Requires-Python: >=3.6
Requires-Dist: pyperclip
